wlc/__init__.py
wlc/config.py
wlc/main.py
wlc/py.typed
wlc/test_base.py
wlc/test_config.py
wlc/test_main.py
wlc/test_utils.py
wlc/test_wlc.py
wlc/utils.py
wlc/test_data/.weblate
wlc/test_data/section
wlc/test_data/weblate.ini
wlc/test_data/wlc
wlc/test_data/api/categories
wlc/test_data/api/categories-1
wlc/test_data/api/changes
wlc/test_data/api/components
wlc/test_data/api/components-hello-android
wlc/test_data/api/components-hello-android-file
wlc/test_data/api/components-hello-android-file--GET--format=zip
wlc/test_data/api/components-hello-olderweblate
wlc/test_data/api/components-hello-weblate
wlc/test_data/api/components-hello-weblate--DELETE--
wlc/test_data/api/components-hello-weblate--PATCH--priority=80
wlc/test_data/api/components-hello-weblate-changes
wlc/test_data/api/components-hello-weblate-file
wlc/test_data/api/components-hello-weblate-file--GET--format=zip
wlc/test_data/api/components-hello-weblate-lock
wlc/test_data/api/components-hello-weblate-lock--POST--lock=0
wlc/test_data/api/components-hello-weblate-lock--POST--lock=1
wlc/test_data/api/components-hello-weblate-repository
wlc/test_data/api/components-hello-weblate-repository--POST--operation=cleanup
wlc/test_data/api/components-hello-weblate-repository--POST--operation=commit
wlc/test_data/api/components-hello-weblate-repository--POST--operation=pull
wlc/test_data/api/components-hello-weblate-repository--POST--operation=push
wlc/test_data/api/components-hello-weblate-repository--POST--operation=reset
wlc/test_data/api/components-hello-weblate-statistics
wlc/test_data/api/components-hello-weblate-statistics--GET--page=2
wlc/test_data/api/components-hello-weblate-statistics--GET--page=3
wlc/test_data/api/components-hello-weblate-translations
wlc/test_data/api/components-hello-weblate-translations--GET--page=2
wlc/test_data/api/components-hello-weblate-translations--POST--language_code=nl_BE
wlc/test_data/api/languages
wlc/test_data/api/languages--GET--page=2
wlc-1.17.2.dist-info/licenses/LICENSE
wlc-1.17.2.dist-info/METADATA
wlc-1.17.2.dist-info/WHEEL
wlc-1.17.2.dist-info/entry_points.txt
wlc-1.17.2.dist-info/top_level.txt
wlc-1.17.2.dist-info/RECORD
