Metadata-Version: 2.4
Name: wlc
Version: 1.17.2
Summary: A command-line utility for Weblate, translation tool with tight version control integration
Author-email: Michal Čihař <michal@weblate.org>
License-Expression: GPL-3.0-or-later
Project-URL: Documentation, https://docs.weblate.org/
Project-URL: Download, https://github.com/WeblateOrg/wlc
Project-URL: Funding, https://weblate.org/donate/
Project-URL: Homepage, https://weblate.org/
Project-URL: Issue Tracker, https://github.com/WeblateOrg/wlc/issues
Project-URL: Source Code, https://github.com/WeblateOrg/wlc
Project-URL: Twitter, https://twitter.com/WeblateOrg
Keywords: i18n,l10n,gettext,git,mercurial,translate
Platform: any
Classifier: Development Status :: 5 - Production/Stable
Classifier: Intended Audience :: Developers
Classifier: Operating System :: OS Independent
Classifier: Programming Language :: Python
Classifier: Programming Language :: Python :: 3
Classifier: Programming Language :: Python :: 3 :: Only
Classifier: Programming Language :: Python :: 3.10
Classifier: Programming Language :: Python :: 3.11
Classifier: Programming Language :: Python :: 3.12
Classifier: Programming Language :: Python :: 3.13
Classifier: Programming Language :: Python :: 3.14
Classifier: Topic :: Software Development :: Internationalization
Classifier: Topic :: Software Development :: Localization
Classifier: Topic :: Utilities
Requires-Python: >=3.10
License-File: LICENSE
Requires-Dist: argcomplete
Requires-Dist: python-dateutil
Requires-Dist: pyxdg
Requires-Dist: requests>=2.25.0
Requires-Dist: urllib3>=1.26
Dynamic: license-file
